{ "students": [
    {
        "id": 1,
        "name": "Aidan Lincoln",
        "have": false
    },
    {
        "id": 2,
        "name": "Chris Wagstaffe",
        "have": false
    },
    {
        "id": 3,
        "name": "Clarion Heard",
        "have": true
    },
    {
        "id": 4,
        "name": "David Perekopskiy",
        "have": false
    },
    {
        "id": 5,
        "name": "Diana Wendt",
        "have": true
    },
    {
        "id": 6,
        "name": "Jack Cole",
        "have": true
    },
    {
        "id": 7,
        "name": "Jazz D Bozner",
        "have": false
    },
    {
        "id": 8,
        "name": "Jonny Riecke",
        "have": true
    },
    {
        "id": 9,
        "name": "Joseph Avila",
        "have": false
    },
    {
        "id": 10,
        "name": "Kailana Kahawaii",
        "have": true
    },
    {
        "id": 11,
        "name": "Lief Friedrichs",
        "have": true
    },
    {
        "id": 12,
        "name": "Matt Milton",
        "have": false
    },
    {
        "id": 13,
        "name": "Kim Khong",
        "have": false
    },
    {
        "id": 14,
        "name": "Zeb Blackwell",
        "have": true
    }
]

}